odoo8_addon_website_crm_quick_answer-8.0.1.0.0.99.dev12-py2.7-nspkg.pth
odoo8_addon_website_crm_quick_answer-8.0.1.0.0.99.dev12.dist-info/DESCRIPTION.rst
odoo8_addon_website_crm_quick_answer-8.0.1.0.0.99.dev12.dist-info/METADATA
odoo8_addon_website_crm_quick_answer-8.0.1.0.0.99.dev12.dist-info/RECORD
odoo8_addon_website_crm_quick_answer-8.0.1.0.0.99.dev12.dist-info/WHEEL
odoo8_addon_website_crm_quick_answer-8.0.1.0.0.99.dev12.dist-info/metadata.json
odoo8_addon_website_crm_quick_answer-8.0.1.0.0.99.dev12.dist-info/namespace_packages.txt
odoo8_addon_website_crm_quick_answer-8.0.1.0.0.99.dev12.dist-info/top_level.txt
odoo_addons/website_crm_quick_answer/README.rst
odoo_addons/website_crm_quick_answer/__init__.py
odoo_addons/website_crm_quick_answer/__openerp__.py
odoo_addons/website_crm_quick_answer/data/automation.xml
odoo_addons/website_crm_quick_answer/i18n/ca.po
odoo_addons/website_crm_quick_answer/i18n/de.po
odoo_addons/website_crm_quick_answer/i18n/el_GR.po
odoo_addons/website_crm_quick_answer/i18n/es.po
odoo_addons/website_crm_quick_answer/i18n/fr.po
odoo_addons/website_crm_quick_answer/i18n/it.po
odoo_addons/website_crm_quick_answer/i18n/pt_BR.po
odoo_addons/website_crm_quick_answer/i18n/sl.po
odoo_addons/website_crm_quick_answer/i18n/website_crm_quick_answer.pot
odoo_addons/website_crm_quick_answer/static/description/icon.png
